bloomy/__init__.py
bloomy/async_client.py
bloomy/client.py
bloomy/configuration.py
bloomy/exceptions.py
bloomy/models.py
bloomy/py.typed
bloomy/operations/__init__.py
bloomy/operations/goals.py
bloomy/operations/headlines.py
bloomy/operations/issues.py
bloomy/operations/meetings.py
bloomy/operations/scorecard.py
bloomy/operations/todos.py
bloomy/operations/users.py
bloomy/operations/async_/__init__.py
bloomy/operations/async_/goals.py
bloomy/operations/async_/headlines.py
bloomy/operations/async_/issues.py
bloomy/operations/async_/meetings.py
bloomy/operations/async_/scorecard.py
bloomy/operations/async_/todos.py
bloomy/operations/async_/users.py
bloomy/operations/mixins/__init__.py
bloomy/operations/mixins/users.py
bloomy/utils/__init__.py
bloomy/utils/abstract_operations.py
bloomy/utils/async_base_operations.py
bloomy/utils/base_operations.py
bloomy_python-0.18.0.dist-info/METADATA
bloomy_python-0.18.0.dist-info/WHEEL
bloomy_python-0.18.0.dist-info/licenses/LICENSE
bloomy_python-0.18.0.dist-info/RECORD
