Metadata-Version: 2.4
Name: bloomy-python
Version: 0.18.0
Summary: Python SDK for Bloom Growth API
Author-email: Franccesco Orozco <franccesco@codingdose.info>
License-File: LICENSE
Requires-Python: >=3.12
Requires-Dist: httpx>=0.27.0
Requires-Dist: pydantic>=2.0.0
Requires-Dist: pyyaml>=6.0
Requires-Dist: typing-extensions>=4.0.0
Provides-Extra: dev
Requires-Dist: pyright>=1.1.0; extra == 'dev'
Requires-Dist: pytest-asyncio>=0.23.0; extra == 'dev'
Requires-Dist: pytest-cov>=5.0.0; extra == 'dev'
Requires-Dist: pytest>=8.0.0; extra == 'dev'
Requires-Dist: ruff>=0.5.0; extra == 'dev'
